setup.py
ajk_ios_buildTools.egg-info/PKG-INFO
ajk_ios_buildTools.egg-info/SOURCES.txt
ajk_ios_buildTools.egg-info/dependency_links.txt
ajk_ios_buildTools.egg-info/not-zip-safe
ajk_ios_buildTools.egg-info/top_level.txt
bin/dailyBuild
bin/getAll
buildTools/__init__.py
buildTools/appManager.py
buildTools/config.py
buildTools/dailyBuild.py
buildTools/deviceManager.py
buildTools/functions.py
buildTools/profileManager.py
buildTools/versionManager.py