Metadata-Version: 1.0
Name: ajk-ios-buildTools
Version: 0.1
Summary: for daily build,RC test...
Home-page: git@github.com:wadecong/buildTools_py_ios.git
Author: Wade Cong
Author-email: eva0612017@126.com
License: MIT
Platform: UNKNOWN
